LICENSE
MANIFEST.in
README.rst
setup.py
django_xadmin_extras.egg-info/PKG-INFO
django_xadmin_extras.egg-info/SOURCES.txt
django_xadmin_extras.egg-info/dependency_links.txt
django_xadmin_extras.egg-info/not-zip-safe
django_xadmin_extras.egg-info/top_level.txt
xadmin_extras/__init__.py
xadmin_extras/apps.py
xadmin_extras/views.py
xadmin_extras/widgets.py
xadmin_extras/wizard.py
xadmin_extras/django_hstore/__init__.py
xadmin_extras/django_hstore/widgets.py
xadmin_extras/ext/__init__.py
xadmin_extras/ext/celery/__init__.py
xadmin_extras/ext/mailfactory/__init__.py
xadmin_extras/ext/mailfactory/utils.py
xadmin_extras/ext/settings/__init__.py
xadmin_extras/static/xadmin/vendor/django-hstore/hstore-xadmin-widget.js
xadmin_extras/templates/hstore_xadmin_widget.html