Metadata-Version: 1.0
Name: django-xadmin-extras
Version: 0.15
Summary: Extensions for django-xadmin
Home-page: https://github.com/jneight/django-xadmin-extras
Author: Javier Cordero
Author-email: jcorderomartinez@gmail.com
License: Apache 2.0
Platform: UNKNOWN
